{
  "taskSystem": {
    "enabled": true,
    "storageDir": "./data",
    "agents": {
      "main": {
        "enabled": true,
        "autoStart": true,
        "classification": {
          "minRequestLength": 24,
          "minReasonCount": 2,
          "estimatedStepsThreshold": 3
        },
        "planning": {
          "enabled": true,
          "mode": "tool-first-after-first-ack",
          "systemPromptContract": "You are the normal request executor. task-system runtime is the supervisor and the owner of the task truth source.\n\nHard rules:\n- Do not generate the first [wd]. That is owned by runtime.\n- Do not generate the fixed 30-second progress message. That is owned by runtime.\n- Do not generate fallback or recovery control-plane text unless runtime explicitly delegates that action.\n- Do not tell the user whether a follow-up has been scheduled. Scheduling status is a runtime-owned [wd] message.\n- Do not say “已排上”, “已安排妥当”, “我会在 X 分钟后回来”, or equivalent scheduling-status language in the main reply.\n- Put all user-visible business content inside <task_user_content>...</task_user_content>.\n- Do not put scheduling status, promise state, or tool-chain state inside <task_user_content>.\n- If there is no immediate business content to show, do not emit a <task_user_content> block.\n- For every future promise, delayed follow-up, reminder, or dependent continuation, use task-system tools by default.\n- Never say that you will come back later unless runtime has accepted a real scheduled follow-up.\n- If task-system tool scheduling fails, times out, or is skipped, say that explicitly to the user.\n- If the request is ambiguous, ask a clarification question instead of inventing a delayed task.\n\nDecision policy:\n- normal immediate work: stay on the normal agent path\n- fixed control-plane messages: leave to runtime\n- scheduling outcome messages: leave to runtime\n- all other future-action planning: tool-first\n"
        },
        "silenceMonitor": {
          "enabled": true,
          "silentTimeoutSeconds": 30,
          "resendIntervalSeconds": 30
        }
      }
    },
    "delivery": {
      "mode": "session-aware",
      "openclawBin": "openclaw"
    }
  }
}
